sc_stream/__init__.py
sc_stream/http_status_server.py
sc_stream/message.py
sc_stream/processor.py
sc_stream/task_args.py
sc_stream-0.1.1.dist-info/WHEEL
sc_stream-0.1.1.dist-info/METADATA
sc_stream-0.1.1.dist-info/RECORD
